calculatorpackage/__init__.py
calculatorpackage/calculator.py
calculatorpackage/calculator_tests.py
Python_Calculator_by_John_Osilama-0.0.2.dist-info/LICENSE
Python_Calculator_by_John_Osilama-0.0.2.dist-info/METADATA
Python_Calculator_by_John_Osilama-0.0.2.dist-info/WHEEL
Python_Calculator_by_John_Osilama-0.0.2.dist-info/top_level.txt
Python_Calculator_by_John_Osilama-0.0.2.dist-info/RECORD
